pt_lightning_sphinx_theme/__init__.py
pt_lightning_sphinx_theme/breadcrumbs.html
pt_lightning_sphinx_theme/cookie_banner.html
pt_lightning_sphinx_theme/fonts.html
pt_lightning_sphinx_theme/footer.html
pt_lightning_sphinx_theme/layout.html
pt_lightning_sphinx_theme/search.html
pt_lightning_sphinx_theme/searchbox.html
pt_lightning_sphinx_theme/theme.conf
pt_lightning_sphinx_theme/theme_variables.jinja
pt_lightning_sphinx_theme/versions.html
pt_lightning_sphinx_theme/static/css/theme.css
pt_lightning_sphinx_theme/static/fonts/FreightSans/freight-sans-bold-italic.woff
pt_lightning_sphinx_theme/static/fonts/FreightSans/freight-sans-bold-italic.woff2
pt_lightning_sphinx_theme/static/fonts/FreightSans/freight-sans-bold.woff
pt_lightning_sphinx_theme/static/fonts/FreightSans/freight-sans-bold.woff2
pt_lightning_sphinx_theme/static/fonts/FreightSans/freight-sans-book-italic.woff
pt_lightning_sphinx_theme/static/fonts/FreightSans/freight-sans-book-italic.woff2
pt_lightning_sphinx_theme/static/fonts/FreightSans/freight-sans-book.woff
pt_lightning_sphinx_theme/static/fonts/FreightSans/freight-sans-book.woff2
pt_lightning_sphinx_theme/static/fonts/FreightSans/freight-sans-light-italic.woff
pt_lightning_sphinx_theme/static/fonts/FreightSans/freight-sans-light-italic.woff2
pt_lightning_sphinx_theme/static/fonts/FreightSans/freight-sans-light.woff
pt_lightning_sphinx_theme/static/fonts/FreightSans/freight-sans-light.woff2
pt_lightning_sphinx_theme/static/fonts/FreightSans/freight-sans-medium-italic.woff
pt_lightning_sphinx_theme/static/fonts/FreightSans/freight-sans-medium-italic.woff2
pt_lightning_sphinx_theme/static/fonts/FreightSans/freight-sans-medium.woff
pt_lightning_sphinx_theme/static/fonts/FreightSans/freight-sans-medium.woff2
pt_lightning_sphinx_theme/static/fonts/IBMPlexMono/IBMPlexMono-Light.woff
pt_lightning_sphinx_theme/static/fonts/IBMPlexMono/IBMPlexMono-Light.woff2
pt_lightning_sphinx_theme/static/fonts/IBMPlexMono/IBMPlexMono-Medium.woff
unofficial_pt_lightning_sphinx_theme-0.0.27.4.dist-info/LICENSE
unofficial_pt_lightning_sphinx_theme-0.0.27.4.dist-info/METADATA
unofficial_pt_lightning_sphinx_theme-0.0.27.4.dist-info/WHEEL
unofficial_pt_lightning_sphinx_theme-0.0.27.4.dist-info/entry_points.txt
unofficial_pt_lightning_sphinx_theme-0.0.27.4.dist-info/top_level.txt
unofficial_pt_lightning_sphinx_theme-0.0.27.4.dist-info/RECORD
